{
 "aggregate_function_based_on": "duration",
 "creation": "2023-10-17 12:00:16.893335",
 "docstatus": 0,
 "doctype": "Number Card",
 "document_type": "Data Overview",
 "dynamic_filters_json": "{}",
 "filters_json": "{}",
 "function": "Sum",
 "idx": 1,
 "is_public": 1,
 "is_standard": 1,
 "label": "Total no of participant in camp",
 "modified": "2023-10-17 12:31:51.872568",
 "modified_by": "Administrator",
 "module": "Epms",
 "name": "Total no of participant in camp",
 "owner": "Administrator",
 "parent_document_type": "",
 "report_field": "number_of_participants",
 "report_function": "Sum",
 "report_name": "No. of Participant in camp",
 "show_percentage_stats": 1,
 "stats_time_interval": "Daily",
 "type": "Report"
}