[
 {
  "docstatus": 0,
  "doctype": "Current location",
  "modified": "2023-09-26 13:13:25.890477",
  "name": "Wazirabad",
  "name_of_location": "Wazirabad"
 },
 {
  "docstatus": 0,
  "doctype": "Current location",
  "modified": "2023-09-26 13:13:59.093453",
  "name": "Vishkarma Colony",
  "name_of_location": "Vishkarma Colony"
 },
 {
  "docstatus": 0,
  "doctype": "Current location",
  "modified": "2023-09-26 13:14:58.392392",
  "name": "Visaya Harijan Chaupal",
  "name_of_location": "Visaya Harijan Chaupal"
 },
 {
  "docstatus": 0,
  "doctype": "Current location",
  "modified": "2023-09-26 13:15:20.384711",
  "name": "Vikash Nagar",
  "name_of_location": "Vikash Nagar"
 },
 {
  "docstatus": 0,
  "doctype": "Current location",
  "modified": "2023-09-26 13:15:36.121535",
  "name": "Shivji Park",
  "name_of_location": "Shivji Park"
 },
 {
  "docstatus": 0,
  "doctype": "Current location",
  "modified": "2023-09-26 13:16:23.328521",
  "name": "Shivaji Park",
  "name_of_location": "Shivaji Park"
 },
 {
  "docstatus": 0,
  "doctype": "Current location",
  "modified": "2023-09-26 13:16:39.868107",
  "name": "Shiv Nagar",
  "name_of_location": "Shiv Nagar"
 },
 {
  "docstatus": 0,
  "doctype": "Current location",
  "modified": "2023-09-26 13:17:00.782690",
  "name": "Shakti Park",
  "name_of_location": "Shakti Park"
 },
 {
  "docstatus": 0,
  "doctype": "Current location",
  "modified": "2023-09-26 13:17:08.392905",
  "name": "Sec -10",
  "name_of_location": "Sec -10"
 },
 {
  "docstatus": 0,
  "doctype": "Current location",
  "modified": "2023-09-26 13:17:42.028080",
  "name": "Roopa Naharpur",
  "name_of_location": "Roopa Naharpur"
 },
 {
  "docstatus": 0,
  "doctype": "Current location",
  "modified": "2023-09-26 13:18:13.839940",
  "name": "Rajasthani Colony",
  "name_of_location": "Rajasthani Colony"
 },
 {
  "docstatus": 0,
  "doctype": "Current location",
  "modified": "2023-09-26 13:18:32.296315",
  "name": "Om Vihar",
  "name_of_location": "Om Vihar"
 },
 {
  "docstatus": 0,
  "doctype": "Current location",
  "modified": "2023-09-26 13:18:42.975217",
  "name": "Om Nagar",
  "name_of_location": "Om Nagar"
 },
 {
  "docstatus": 0,
  "doctype": "Current location",
  "modified": "2023-09-26 13:18:59.202943",
  "name": "Nai Basti",
  "name_of_location": "Nai Basti"
 },
 {
  "docstatus": 0,
  "doctype": "Current location",
  "modified": "2023-09-26 13:19:19.664487",
  "name": "Madanpuri",
  "name_of_location": "Madanpuri"
 },
 {
  "docstatus": 0,
  "doctype": "Current location",
  "modified": "2023-09-26 13:19:36.662856",
  "name": "Laxmi Garden",
  "name_of_location": "Laxmi Garden"
 },
 {
  "docstatus": 0,
  "doctype": "Current location",
  "modified": "2023-09-26 13:20:00.336448",
  "name": "Krishna Colony",
  "name_of_location": "Krishna Colony"
 },
 {
  "docstatus": 0,
  "doctype": "Current location",
  "modified": "2023-09-26 13:20:23.278592",
  "name": "Khandas Road",
  "name_of_location": "Khandas Road"
 },
 {
  "docstatus": 0,
  "doctype": "Current location",
  "modified": "2023-09-26 13:20:39.906807",
  "name": "Kadipur",
  "name_of_location": "Kadipur"
 },
 {
  "docstatus": 0,
  "doctype": "Current location",
  "modified": "2023-09-26 13:21:08.423889",
  "name": "Islampur",
  "name_of_location": "Islampur"
 },
 {
  "docstatus": 0,
  "doctype": "Current location",
  "modified": "2023-09-26 13:21:18.319866",
  "name": "Heera Nagar",
  "name_of_location": "Heera Nagar"
 },
 {
  "docstatus": 0,
  "doctype": "Current location",
  "modified": "2023-09-26 13:21:27.961604",
  "name": "Hari Nagar",
  "name_of_location": "Hari Nagar"
 },
 {
  "docstatus": 0,
  "doctype": "Current location",
  "modified": "2023-09-26 13:21:42.223234",
  "name": "Gandhinagar",
  "name_of_location": "Gandhinagar"
 },
 {
  "docstatus": 0,
  "doctype": "Current location",
  "modified": "2023-09-26 13:22:04.908039",
  "name": "Devilal Colony",
  "name_of_location": "Devilal Colony"
 },
 {
  "docstatus": 0,
  "doctype": "Current location",
  "modified": "2023-09-26 13:22:28.656427",
  "name": "Bhawani Enclave",
  "name_of_location": "Bhawani Enclave"
 },
 {
  "docstatus": 0,
  "doctype": "Current location",
  "modified": "2023-09-26 13:22:41.631585",
  "name": "Basai Road",
  "name_of_location": "Basai Road"
 },
 {
  "docstatus": 0,
  "doctype": "Current location",
  "modified": "2023-09-26 13:23:00.564160",
  "name": "Basai Enclave",
  "name_of_location": "Basai Enclave"
 },
 {
  "docstatus": 0,
  "doctype": "Current location",
  "modified": "2023-09-26 13:23:16.608242",
  "name": "Amar Colony",
  "name_of_location": "Amar Colony"
 },
 {
  "docstatus": 0,
  "doctype": "Current location",
  "modified": "2023-09-26 13:23:28.444920",
  "name": "Arjun Nagar",
  "name_of_location": "Arjun Nagar"
 },
 {
  "docstatus": 0,
  "doctype": "Current location",
  "modified": "2023-09-26 13:24:00.104921",
  "name": "Firoz Gandhi Colony",
  "name_of_location": "Firoz Gandhi Colony"
 },
 {
  "docstatus": 0,
  "doctype": "Current location",
  "modified": "2023-09-26 13:24:09.313318",
  "name": "Ravi Nagar",
  "name_of_location": "Ravi Nagar"
 },
 {
    "docstatus": 0,
    "doctype": "Current location",
    "modified": "2023-09-26 13:18:22.057640",
    "name": "Others",
    "name_of_location": "Others"
}
]